tobe_time_mcp/__init__.py
tobe_time_mcp/server.py
mcp_ly_test-0.1.0.dist-info/METADATA
mcp_ly_test-0.1.0.dist-info/WHEEL
mcp_ly_test-0.1.0.dist-info/entry_points.txt
mcp_ly_test-0.1.0.dist-info/top_level.txt
mcp_ly_test-0.1.0.dist-info/RECORD
