Metadata-Version: 2.4
Name: mcp-ly-test
Version: 0.1.0
Summary: The MCP server to get local time
Requires-Python: >=3.13
Requires-Dist: fastmcp>=2.12.2
